hero_api_service/__init__.py
hero_api_service/hero_api.py
hero_api_service/py.typed
hero_api_service/models/__init__.py
hero_api_service/models/hero_api_error_model.py
hero_api_service/models/hero_api_list_model.py
hero_api_service/models/hero_api_model.py
hero_api_service-0.1.4.dist-info/METADATA
hero_api_service-0.1.4.dist-info/WHEEL
hero_api_service-0.1.4.dist-info/RECORD
