Metadata-Version: 2.4
Name: hero-api-service
Version: 0.1.4
Summary: Transform services in default endpoints integrated by FastAPI and Pydantic.
Requires-Python: >=3.10.0
Requires-Dist: fastapi>=0.115.12
Requires-Dist: pydantic>=2.11.5
